road_collisions_france/__init__.py
road_collisions_france/bin/__init__.py
road_collisions_france/bin/load.py
road_collisions_france/models/__init__.py
road_collisions_france/models/casualty.py
road_collisions_france/models/collision.py
road_collisions_france/models/vehicle.py
road_collisions_france/resources/fr/fr.csv.tgz
road_collisions_france-0.0.3.dist-info/METADATA
road_collisions_france-0.0.3.dist-info/WHEEL
road_collisions_france-0.0.3.dist-info/entry_points.txt
road_collisions_france-0.0.3.dist-info/top_level.txt
road_collisions_france-0.0.3.dist-info/RECORD
