Metadata-Version: 2.1
Name: road-collisions-france
Version: 0.0.3
Summary: Road collision data for France
Home-page: https://github.com/RobertLucey/road-collisions-france
Author: Robert Lucey
License: UNKNOWN
Platform: UNKNOWN
Requires-Python: >=3.6
Requires-Dist: road-collisions-base
